{
  "chave": "17250100749616000160550010000580221025725193",
  "num_nota": "58022",
  "produtos": [
    {
      "chave_nfe": "17250100749616000160550010000580221025725193",
      "num_item": "",
      "codigo": "GD0000133327",
      "ean": "7891019177110",
      "descricao": "DC SE AC PALHA - RM RM844 P 16L",
      "ncm": "32091010",
      "cest": "2400100",
      "cfop": "5405",
      "unidade": "LT",
      "quantidade": 1.0,
      "valor_unitario": 630.0,
      "valor_total": 630.0,
      "icms_cst": "60",
      "icms_aliq": 0.0,
      "icms_valor": 0.0,
      "icms_st_valor": 0.0,
      "icms_st_bc": 0.0,
      "ipi_cst": "",
      "ipi_aliq": 0.0,
      "ipi_valor": 0.0,
      "pis_cst": "01",
      "pis_aliq": 0.65,
      "pis_valor": 4.1,
      "cofins_cst": "01",
      "cofins_aliq": 3.0,
      "cofins_valor": 18.9
    },
    {
      "chave_nfe": "17250100749616000160550010000580221025725193",
      "num_item": "",
      "codigo": "700",
      "ean": "7891019138456",
      "descricao": "CORALAR ACR.FOSCO BR NEVE 3,6LT",
      "ncm": "32091010",
      "cest": "2400100",
      "cfop": "5405",
      "unidade": "GL",
      "quantidade": 1.0,
      "valor_unitario": 90.0,
      "valor_total": 90.0,
      "icms_cst": "60",
      "icms_aliq": 0.0,
      "icms_valor": 0.0,
      "icms_st_valor": 0.0,
      "icms_st_bc": 0.0,
      "ipi_cst": "",
      "ipi_aliq": 0.0,
      "ipi_valor": 0.0,
      "pis_cst": "01",
      "pis_aliq": 0.65,
      "pis_valor": 0.59,
      "cofins_cst": "01",
      "cofins_aliq": 3.0,
      "cofins_valor": 2.7
    },
    {
      "chave_nfe": "17250100749616000160550010000580221025725193",
      "num_item": "",
      "codigo": "7316",
      "ean": "7898619765648",
      "descricao": "KOKAR STD FS ULTRA REND 18LT TITANIO",
      "ncm": "32091010",
      "cest": "2400100",
      "cfop": "5405",
      "unidade": "LT",
      "quantidade": 1.0,
      "valor_unitario": 350.0,
      "valor_total": 350.0,
      "icms_cst": "60",
      "icms_aliq": 0.0,
      "icms_valor": 0.0,
      "icms_st_valor": 0.0,
      "icms_st_bc": 0.0,
      "ipi_cst": "",
      "ipi_aliq": 0.0,
      "ipi_valor": 0.0,
      "pis_cst": "01",
      "pis_aliq": 0.65,
      "pis_valor": 2.28,
      "cofins_cst": "01",
      "cofins_aliq": 3.0,
      "cofins_valor": 10.5
    },
    {
      "chave_nfe": "17250100749616000160550010000580221025725193",
      "num_item": "",
      "codigo": "8120",
      "ean": "7898619765990",
      "descricao": "KOKAR FUNDO PREPARADOR DE PAREDES FIT 3,6LT",
      "ncm": "32091010",
      "cest": "2400100",
      "cfop": "5405",
      "unidade": "GL",
      "quantidade": 1.0,
      "valor_unitario": 60.0,
      "valor_total": 60.0,
      "icms_cst": "60",
      "icms_aliq": 0.0,
      "icms_valor": 0.0,
      "icms_st_valor": 0.0,
      "icms_st_bc": 0.0,
      "ipi_cst": "",
      "ipi_aliq": 0.0,
      "ipi_valor": 0.0,
      "pis_cst": "01",
      "pis_aliq": 0.65,
      "pis_valor": 0.39,
      "cofins_cst": "01",
      "cofins_aliq": 3.0,
      "cofins_valor": 1.8
    }
  ]
}