{
  "chave": "17250100749616000160550010000580321025728520",
  "num_nota": "58032",
  "produtos": [
    {
      "chave_nfe": "17250100749616000160550010000580321025728520",
      "num_item": "",
      "codigo": "6115",
      "ean": "7896603804243",
      "descricao": "FITA CREPE ADELBRAS AZUL 24X50M 722",
      "ncm": "48114110",
      "cest": "",
      "cfop": "5102",
      "unidade": "UN",
      "quantidade": 2.0,
      "valor_unitario": 18.0,
      "valor_total": 36.0,
      "icms_cst": "00",
      "icms_aliq": 20.0,
      "icms_valor": 7.2,
      "icms_st_valor": 0.0,
      "icms_st_bc": 0.0,
      "ipi_cst": "",
      "ipi_aliq": 0.0,
      "ipi_valor": 0.0,
      "pis_cst": "01",
      "pis_aliq": 0.65,
      "pis_valor": 0.19,
      "cofins_cst": "01",
      "cofins_aliq": 3.0,
      "cofins_valor": 0.86
    },
    {
      "chave_nfe": "17250100749616000160550010000580321025728520",
      "num_item": "",
      "codigo": "6116",
      "ean": "7896603804250",
      "descricao": "FITA CREPE ADELBRAS AZUL 48X50M 722",
      "ncm": "48114110",
      "cest": "",
      "cfop": "5102",
      "unidade": "UN",
      "quantidade": 4.0,
      "valor_unitario": 35.0,
      "valor_total": 140.0,
      "icms_cst": "00",
      "icms_aliq": 20.0,
      "icms_valor": 28.0,
      "icms_st_valor": 0.0,
      "icms_st_bc": 0.0,
      "ipi_cst": "",
      "ipi_aliq": 0.0,
      "ipi_valor": 0.0,
      "pis_cst": "01",
      "pis_aliq": 0.65,
      "pis_valor": 0.73,
      "cofins_cst": "01",
      "cofins_aliq": 3.0,
      "cofins_valor": 3.36
    },
    {
      "chave_nfe": "17250100749616000160550010000580321025728520",
      "num_item": "",
      "codigo": "3964",
      "ean": "7891055094921",
      "descricao": "CONDOR ROLO PELE DE CARNEIRO 950 23CM EXTRA 25MM",
      "ncm": "96034010",
      "cest": "",
      "cfop": "5102",
      "unidade": "UN",
      "quantidade": 1.0,
      "valor_unitario": 70.0,
      "valor_total": 70.0,
      "icms_cst": "00",
      "icms_aliq": 20.0,
      "icms_valor": 14.0,
      "icms_st_valor": 0.0,
      "icms_st_bc": 0.0,
      "ipi_cst": "",
      "ipi_aliq": 0.0,
      "ipi_valor": 0.0,
      "pis_cst": "01",
      "pis_aliq": 0.65,
      "pis_valor": 0.36,
      "cofins_cst": "01",
      "cofins_aliq": 3.0,
      "cofins_valor": 1.68
    },
    {
      "chave_nfe": "17250100749616000160550010000580321025728520",
      "num_item": "",
      "codigo": "1044",
      "ean": "7896380191642",
      "descricao": "DESEMPENADEIRA 165 PVC GRANDE ATLAS",
      "ncm": "39269090",
      "cest": "",
      "cfop": "5102",
      "unidade": "UN",
      "quantidade": 1.0,
      "valor_unitario": 31.5,
      "valor_total": 31.5,
      "icms_cst": "00",
      "icms_aliq": 20.0,
      "icms_valor": 6.3,
      "icms_st_valor": 0.0,
      "icms_st_bc": 0.0,
      "ipi_cst": "",
      "ipi_aliq": 0.0,
      "ipi_valor": 0.0,
      "pis_cst": "01",
      "pis_aliq": 0.65,
      "pis_valor": 0.16,
      "cofins_cst": "01",
      "cofins_aliq": 3.0,
      "cofins_valor": 0.76
    },
    {
      "chave_nfe": "17250100749616000160550010000580321025728520",
      "num_item": "",
      "codigo": "11152",
      "ean": "7898667209293",
      "descricao": "KOKAR 123 IMPERM 16LT BRANCO",
      "ncm": "32091020",
      "cest": "2400100",
      "cfop": "5405",
      "unidade": "BD",
      "quantidade": 2.0,
      "valor_unitario": 330.0,
      "valor_total": 660.0,
      "icms_cst": "60",
      "icms_aliq": 0.0,
      "icms_valor": 0.0,
      "icms_st_valor": 0.0,
      "icms_st_bc": 0.0,
      "ipi_cst": "",
      "ipi_aliq": 0.0,
      "ipi_valor": 0.0,
      "pis_cst": "01",
      "pis_aliq": 0.65,
      "pis_valor": 4.29,
      "cofins_cst": "01",
      "cofins_aliq": 3.0,
      "cofins_valor": 19.8
    },
    {
      "chave_nfe": "17250100749616000160550010000580321025728520",
      "num_item": "",
      "codigo": "8544",
      "ean": "7898667207299",
      "descricao": "KOKAR TEXTURA RISCADO BALDE 20KG BRANCO NATURAL*R",
      "ncm": "32091010",
      "cest": "2400100",
      "cfop": "5405",
      "unidade": "BD",
      "quantidade": 9.0,
      "valor_unitario": 112.5,
      "valor_total": 1012.5,
      "icms_cst": "60",
      "icms_aliq": 0.0,
      "icms_valor": 0.0,
      "icms_st_valor": 0.0,
      "icms_st_bc": 0.0,
      "ipi_cst": "",
      "ipi_aliq": 0.0,
      "ipi_valor": 0.0,
      "pis_cst": "01",
      "pis_aliq": 0.65,
      "pis_valor": 6.58,
      "cofins_cst": "01",
      "cofins_aliq": 3.0,
      "cofins_valor": 30.38
    },
    {
      "chave_nfe": "17250100749616000160550010000580321025728520",
      "num_item": "",
      "codigo": "GD0000273061",
      "ean": "7898667209293",
      "descricao": "KOKAR 123 IMPERM. CINZA GA 30YY 42 083 5319 P 16L",
      "ncm": "32091020",
      "cest": "2400100",
      "cfop": "5405",
      "unidade": "BD",
      "quantidade": 1.0,
      "valor_unitario": 380.0,
      "valor_total": 380.0,
      "icms_cst": "60",
      "icms_aliq": 0.0,
      "icms_valor": 0.0,
      "icms_st_valor": 0.0,
      "icms_st_bc": 0.0,
      "ipi_cst": "",
      "ipi_aliq": 0.0,
      "ipi_valor": 0.0,
      "pis_cst": "01",
      "pis_aliq": 0.65,
      "pis_valor": 2.47,
      "cofins_cst": "01",
      "cofins_aliq": 3.0,
      "cofins_valor": 11.4
    }
  ]
}